biomedicus/__init__.py
biomedicus/__main__.py
biomedicus/biomedicus-all.jar
biomedicus/cli.py
biomedicus/config.py
biomedicus/data_version.py
biomedicus/defaultConfig.yml
biomedicus/java_support.py
biomedicus/pipeline_service.py
biomedicus/tokenization.py
biomedicus/version.py
biomedicus/core/__init__.py
biomedicus/core/dawg.py
biomedicus/dependencies/__init__.py
biomedicus/dependencies/conllu_reader.py
biomedicus/dependencies/split_conllu.py
biomedicus/dependencies/stanza_parser.py
biomedicus/dependencies/stanza_selective_parser.py
biomedicus/deployment/__init__.py
biomedicus/deployment/_data_downloading.py
biomedicus/deployment/default_deployment.py
biomedicus/deployment/rtf_to_text.py
biomedicus/deployment/confs/__init__.py
biomedicus/deployment/confs/biomedicus_deploy.yml
biomedicus/deployment/confs/rtf_to_text_deploy.yml
biomedicus/deployment/confs/scaleout_deploy.yml
biomedicus/examples/__init__.py
biomedicus/examples/add_pos_tags.py
biomedicus/examples/dependencies.py
biomedicus/examples/mipacq_csv_reader.py
biomedicus/examples/sentences.py
biomedicus/examples/tutorial/__init__.py
biomedicus/examples/tutorial/medications.py
biomedicus/examples/tutorial/sql_pipeline.py
biomedicus/examples/tutorial/sql_pipeline_rtf.py
biomedicus/examples/tutorial/sql_pipeline_rtf_only.py
biomedicus/negation/__init__.py
biomedicus/negation/deepen.py
biomedicus/negation/i2b2_va2010.py
biomedicus/negation/negex.py
biomedicus/negation/negex_triggers.py
biomedicus/negation/negex_triggers.txt
biomedicus/sentences/__init__.py
biomedicus/sentences/bi_lstm.py
biomedicus/sentences/bi_lstm_torchserve.py
biomedicus/sentences/bilstm_handler.py
biomedicus/sentences/input.py
biomedicus/sentences/one_per_line_sentences.py
biomedicus/sentences/vocabulary.py
biomedicus/tagging/__init__.py
biomedicus/tagging/genia_xml_pipeline.py
biomedicus/tagging/ptb_evaluation_set.py
biomedicus/tagging/ptb_pipeline.py
biomedicus/utilities/__init__.py
biomedicus/utilities/embeddings.py
biomedicus-3.4.3.dist-info/LICENSE.txt
biomedicus-3.4.3.dist-info/METADATA
biomedicus-3.4.3.dist-info/WHEEL
biomedicus-3.4.3.dist-info/entry_points.txt
biomedicus-3.4.3.dist-info/top_level.txt
biomedicus-3.4.3.dist-info/RECORD
