Metadata-Version: 2.1
Name: biomedicus
Version: 3.4.3
Summary: A biomedical and clinical natural language processing engine.
Author-email: University of Minnesota NLP/IE Group <nlp-ie@umn.edu>, Ben Knoll <benknoll@umn.edu>
License: 
Project-URL: homepage, https://nlpie.github.io/biomedicus
Project-URL: documentation, https://nlpie.github.io/biomedicus/guides
Project-URL: repository, https://github.com/nlpie/biomedicus3.git
Classifier: Development Status :: 4 - Beta
Classifier: Environment :: Console
Classifier: Intended Audience :: Healthcare Industry
Classifier: Intended Audience :: Information Technology
Classifier: Intended Audience :: Science/Research
Classifier: License :: OSI Approved :: Apache Software License
Classifier: Natural Language :: English
Classifier: Operating System :: MacOS :: MacOS X
Classifier: Operating System :: POSIX :: Linux
Classifier: Programming Language :: Java
Classifier: Programming Language :: Python :: 3 :: Only
Classifier: Programming Language :: Python :: 3.9
Classifier: Programming Language :: Python :: 3.10
Classifier: Programming Language :: Python :: 3.11
Classifier: Programming Language :: Python :: Implementation :: CPython
Classifier: Topic :: Scientific/Engineering :: Information Analysis
Classifier: Topic :: Scientific/Engineering :: Medical Science Apps.
Classifier: Topic :: Text Processing :: General
Classifier: Topic :: Text Processing :: Linguistic
Requires-Python: >=3.9
License-File: LICENSE.txt
Requires-Dist: biomedicus-client==3.4.3
Requires-Dist: numpy==2.0.2
Requires-Dist: regex==2024.9.11
Requires-Dist: torch==2.4.1
Requires-Dist: requests==2.32.3
Requires-Dist: watchdog==5.0.3
Provides-Extra: stanza
Requires-Dist: stanza==1.9.2; extra == "stanza"
Provides-Extra: test
Requires-Dist: pytest==8.3.3; extra == "test"
